htask/__init__.py
htask/module.py
htask-1.0.dist-info/LICENCE
htask-1.0.dist-info/METADATA
htask-1.0.dist-info/WHEEL
htask-1.0.dist-info/top_level.txt
htask-1.0.dist-info/RECORD
