Metadata-Version: 2.1
Name: htask
Version: 1.0
Summary: This project helps to solve basics problems where you stuck every time because these are basic tasks and we forget it everytime then when suddenly asked by someone or during collage projects.This tool covers every basics problems such as fibnacci series , complex patterns, reverse string, find  duplicate values and more. 
Home-page: https://github.com/MrHorbio/
Author: Ankush Kumar Rajput (Mr.Horbio)
License: MIT
Classifier: Programming Language :: Python :: 3
Classifier: License :: OSI Approved :: MIT License
Classifier: Operating System :: OS Independent
Requires-Python: >=3.6
License-File: LICENCE
